{
  "metadata": {
    "expire_time_gmt": 1775906576,
    "language": "en-US",
    "location_id": "KLGA:9:US",
    "status_code": 200,
    "transaction_id": "1775902975348:-1836665373",
    "units": "e",
    "version": "1"
  },
  "observations": [
    {
      "blunt_phrase": null,
      "class": "observation",
      "clds": "FEW",
      "day_ind": "N",
      "dewPt": 37,
      "expire_time_gmt": 1773211860,
      "feels_like": 70,
      "gust": null,
      "heat_index": 70,
      "icon_extd": 3300,
      "key": "KLGA",
      "max_temp": 78,
      "min_temp": 45,
      "obs_id": "KLGA",
      "obs_name": "New York/LaGuardia",
      "precip_hrly": 0,
      "precip_total": null,
      "pressure": 29.95,
      "pressure_desc": null,
      "pressure_tend": null,
      "primary_swell_direction": null,
      "primary_swell_height": null,
      "primary_swell_period": null,
      "primary_wave_height": null,
      "primary_wave_period": null,
      "qualifier": null,
      "qualifier_svrty": null,
      "rh": 30,
      "secondary_swell_direction": null,
      "secondary_swell_height": null,
      "secondary_swell_period": null,
      "snow_hrly": null,
      "temp": 70,
      "terse_phrase": null,
      "uv_desc": "Low",
      "uv_index": 0,
      "valid_time_gmt": 1773204660,
      "vis": 10,
      "water_temp": null,
      "wc": 70,
      "wdir": 210,
      "wdir_cardinal": "SSW",
      "wspd": 9,
      "wx_icon": 33,
      "wx_phrase": "Fair"
    },
    {
      "blunt_phrase": null,
      "class": "observation",
      "clds": "FEW",
      "day_ind": "N",
      "dewPt": 38,
      "expire_time_gmt": 1773215460,
      "feels_like": 66,
      "gust": null,
      "heat_index": 66,
      "icon_extd": 3300,
      "key": "KLGA",
      "max_temp": null,
      "min_temp": null,
      "obs_id": "KLGA",
      "obs_name": "New York/LaGuardia",
      "precip_hrly": 0,
      "precip_total": null,
      "pressure": 29.94,
      "pressure_desc": "Falling Rapidly",
      "pressure_tend": 2,
      "primary_swell_direction": null,
      "primary_swell_height": null,
      "primary_swell_period": null,
      "primary_wave_height": null,
      "primary_wave_period": null,
      "qualifier": null,
      "qualifier_svrty": null,
      "rh": 36,
      "secondary_swell_direction": null,
      "secondary_swell_height": null,
      "secondary_swell_period": null,
      "snow_hrly": null,
      "temp": 66,
      "terse_phrase": null,
      "uv_desc": "Low",
      "uv_index": 0,
      "valid_time_gmt": 1773208260,
      "vis": 10,
      "water_temp": null,
      "wc": 66,
      "wdir": 190,
      "wdir_cardinal": "S",
      "wspd": 6,
      "wx_icon": 33,
      "wx_phrase": "Fair"
    },
    {
      "blunt_phrase": null,
      "class": "observation",
      "clds": "BKN",
      "day_ind": "N",
      "dewPt": 39,
      "expire_time_gmt": 1773219060,
      "feels_like": 60,
      "gust": null,
      "heat_index": 60,
      "icon_extd": 2700,
      "key": "KLGA",
      "max_temp": null,
      "min_temp": null,
      "obs_id": "KLGA",
      "obs_name": "New York/LaGuardia",
      "precip_hrly": 0,
      "precip_total": null,
      "pressure": 29.95,
      "pressure_desc": null,
      "pressure_tend": null,
      "primary_swell_direction": null,
      "primary_swell_height": null,
      "primary_swell_period": null,
      "primary_wave_height": null,
      "primary_wave_period": null,
      "qualifier": null,
      "qualifier_svrty": null,
      "rh": 46,
      "secondary_swell_direction": null,
      "secondary_swell_height": null,
      "secondary_swell_period": null,
      "snow_hrly": null,
      "temp": 60,
      "terse_phrase": null,
      "uv_desc": "Low",
      "uv_index": 0,
      "valid_time_gmt": 1773211860,
      "vis": 10,
      "water_temp": null,
      "wc": 60,
      "wdir": 100,
      "wdir_cardinal": "E",
      "wspd": 7,
      "wx_icon": 27,
      "wx_phrase": "Mostly Cloudy"
    },
    {
      "blunt_phrase": null,
      "class": "observation",
      "clds": "BKN",
      "day_ind": "N",
      "dewPt": 40,
      "expire_time_gmt": 1773222660,
      "feels_like": 52,
      "gust": null,
      "heat_index": 52,
      "icon_extd": 2700,
      "key": "KLGA",
      "max_temp": null,
      "min_temp": null,
      "obs_id": "KLGA",
      "obs_name": "New York/LaGuardia",
      "precip_hrly": 0,
      "precip_total": null,
      "pressure": 29.94,
      "pressure_desc": null,
      "pressure_tend": null,
      "primary_swell_direction": null,
      "primary_swell_height": null,
      "primary_swell_period": null,
      "primary_wave_height": null,
      "primary_wave_period": null,
      "qualifier": null,
      "qualifier_svrty": null,
      "rh": 63,
      "secondary_swell_direction": null,
      "secondary_swell_height": null,
      "secondary_swell_period": null,
      "snow_hrly": null,
      "temp": 52,
      "terse_phrase": null,
      "uv_desc": "Low",
      "uv_index": 0,
      "valid_time_gmt": 1773215460,
      "vis": 10,
      "water_temp": null,
      "wc": 52,
      "wdir": 70,
      "wdir_cardinal": "ENE",
      "wspd": 7,
      "wx_icon": 27,
      "wx_phrase": "Mostly Cloudy"
    },
    {
      "blunt_phrase": null,
      "class": "observation",
      "clds": "FEW",
      "day_ind": "N",
      "dewPt": 40,
      "expire_time_gmt": 1773226260,
      "feels_like": 50,
      "gust": null,
      "heat_index": 50,
      "icon_extd": 3300,
      "key": "KLGA",
      "max_temp": null,
      "min_temp": null,
      "obs_id": "KLGA",
      "obs_name": "New York/LaGuardia",
      "precip_hrly": 0,
      "precip_total": null,
      "pressure": 29.93,
      "pressure_desc": "Falling Rapidly",
      "pressure_tend": 2,
      "primary_swell_direction": null,
      "primary_swell_height": null,
      "primary_swell_period": null,
      "primary_wave_height": null,
      "primary_wave_period": null,
      "qualifier": null,
      "qualifier_svrty": null,
      "rh": 68,
      "secondary_swell_direction": null,
      "secondary_swell_height": null,
      "secondary_swell_period": null,
      "snow_hrly": null,
      "temp": 50,
      "terse_phrase": null,
      "uv_desc": "Low",
      "uv_index": 0,
      "valid_time_gmt": 1773219060,
      "vis": 10,
      "water_temp": null,
      "wc": 50,
      "wdir": 60,
      "wdir_cardinal": "ENE",
      "wspd": 7,
      "wx_icon": 33,
      "wx_phrase": "Fair"
    },
    {
      "blunt_phrase": null,
      "class": "observation",
      "clds": "BKN",
      "day_ind": "N",
      "dewPt": 39,
      "expire_time_gmt": 1773229860,
      "feels_like": 44,
      "gust": null,
      "heat_index": 47,
      "icon_extd": 2700,
      "key": "KLGA",
      "max_temp": null,
      "min_temp": null,
      "obs_id": "KLGA",
      "obs_name": "New York/LaGuardia",
      "precip_hrly": 0,
      "precip_total": null,
      "pressure": 29.93,
      "pressure_desc": null,
      "pressure_tend": null,
      "primary_swell_direction": null,
      "primary_swell_height": null,
      "primary_swell_period": null,
      "primary_wave_height": null,
      "primary_wave_period": null,
      "qualifier": null,
      "qualifier_svrty": null,
      "rh": 74,
      "secondary_swell_direction": null,
      "secondary_swell_height": null,
      "secondary_swell_period": null,
      "snow_hrly": null,
      "temp": 47,
      "terse_phrase": null,
      "uv_desc": "Low",
      "uv_index": 0,
      "valid_time_gmt": 1773222660,
      "vis": 10,
      "water_temp": null,
      "wc": 44,
      "wdir": 70,
      "wdir_cardinal": "ENE",
      "wspd": 7,
      "wx_icon": 27,
      "wx_phrase": "Mostly Cloudy"
    },
    {
      "blunt_phrase": null,
      "class": "observation",
      "clds": "SCT",
      "day_ind": "D",
      "dewPt": 43,
      "expire_time_gmt": 1773233460,
      "feels_like": 54,
      "gust": null,
      "heat_index": 54,
      "icon_extd": 3000,
      "key": "KLGA",
      "max_temp": null,
      "min_temp": null,
      "obs_id": "KLGA",
      "obs_name": "New York/LaGuardia",
      "precip_hrly": 0,
      "precip_total": null,
      "pressure": 29.92,
      "pressure_desc": null,
      "pressure_tend": null,
      "primary_swell_direction": null,
      "primary_swell_height": null,
      "primary_swell_period": null,
      "primary_wave_height": null,
      "primary_wave_period": null,
      "qualifier": null,
      "qualifier_svrty": null,
      "rh": 66,
      "secondary_swell_direction": null,
      "secondary_swell_height": null,
      "secondary_swell_period": null,
      "snow_hrly": null,
      "temp": 54,
      "terse_phrase": null,
      "uv_desc": "Low",
      "uv_index": 0,
      "valid_time_gmt": 1773226260,
      "vis": 10,
      "water_temp": null,
      "wc": 54,
      "wdir": 140,
      "wdir_cardinal": "SE",
      "wspd": 3,
      "wx_icon": 30,
      "wx_phrase": "Partly Cloudy"
    },
    {
      "blunt_phrase": null,
      "class": "observation",
      "clds": "SCT",
      "day_ind": "D",
      "dewPt": 43,
      "expire_time_gmt": 1773237060,
      "feels_like": 53,
      "gust": null,
      "heat_index": 53,
      "icon_extd": 3000,
      "key": "KLGA",
      "max_temp": null,
      "min_temp": null,
      "obs_id": "KLGA",
      "obs_name": "New York/LaGuardia",
      "precip_hrly": 0,
      "precip_total": null,
      "pressure": 29.92,
      "pressure_desc": "Steady",
      "pressure_tend": 0,
      "primary_swell_direction": null,
      "primary_swell_height": null,
      "primary_swell_period": null,
      "primary_wave_height": null,
      "primary_wave_period": null,
      "qualifier": null,
      "qualifier_svrty": null,
      "rh": 69,
      "secondary_swell_direction": null,
      "secondary_swell_height": null,
      "secondary_swell_period": null,
      "snow_hrly": null,
      "temp": 53,
      "terse_phrase": null,
      "uv_desc": "Low",
      "uv_index": 0,
      "valid_time_gmt": 1773229860,
      "vis": 10,
      "water_temp": null,
      "wc": 53,
      "wdir": null,
      "wdir_cardinal": "VAR",
      "wspd": 5,
      "wx_icon": 30,
      "wx_phrase": "Partly Cloudy"
    },
    {
      "blunt_phrase": null,
      "class": "observation",
      "clds": "BKN",
      "day_ind": "D",
      "dewPt": 43,
      "expire_time_gmt": 1773240660,
      "feels_like": 53,
      "gust": null,
      "heat_index": 53,
      "icon_extd": 2800,
      "key": "KLGA",
      "max_temp": null,
      "min_temp": null,
      "obs_id": "KLGA",
      "obs_name": "New York/LaGuardia",
      "precip_hrly": 0,
      "precip_total": null,
      "pressure": 29.92,
      "pressure_desc": null,
      "pressure_tend": null,
      "primary_swell_direction": null,
      "primary_swell_height": null,
      "primary_swell_period": null,
      "primary_wave_height": null,
      "primary_wave_period": null,
      "qualifier": null,
      "qualifier_svrty": null,
      "rh": 69,
      "secondary_swell_direction": null,
      "secondary_swell_height": null,
      "secondary_swell_period": null,
      "snow_hrly": null,
      "temp": 53,
      "terse_phrase": null,
      "uv_desc": "Low",
      "uv_index": 0,
      "valid_time_gmt": 1773233460,
      "vis": 10,
      "water_temp": null,
      "wc": 53,
      "wdir": 90,
      "wdir_cardinal": "E",
      "wspd": 6,
      "wx_icon": 28,
      "wx_phrase": "Mostly Cloudy"
    },
    {
      "blunt_phrase": null,
      "class": "observation",
      "clds": "BKN",
      "day_ind": "D",
      "dewPt": 44,
      "expire_time_gmt": 1773244260,
      "feels_like": 58,
      "gust": null,
      "heat_index": 58,
      "icon_extd": 2800,
      "key": "KLGA",
      "max_temp": null,
      "min_temp": null,
      "obs_id": "KLGA",
      "obs_name": "New York/LaGuardia",
      "precip_hrly": 0,
      "precip_total": null,
      "pressure": 29.91,
      "pressure_desc": null,
      "pressure_tend": null,
      "primary_swell_direction": null,
      "primary_swell_height": null,
      "primary_swell_period": null,
      "primary_wave_height": null,
      "primary_wave_period": null,
      "qualifier": null,
      "qualifier_svrty": null,
      "rh": 60,
      "secondary_swell_direction": null,
      "secondary_swell_height": null,
      "secondary_swell_period": null,
      "snow_hrly": null,
      "temp": 58,
      "terse_phrase": null,
      "uv_desc": "Low",
      "uv_index": 1,
      "valid_time_gmt": 1773237060,
      "vis": 10,
      "water_temp": null,
      "wc": 58,
      "wdir": 130,
      "wdir_cardinal": "SE",
      "wspd": 7,
      "wx_icon": 28,
      "wx_phrase": "Mostly Cloudy"
    },
    {
      "blunt_phrase": null,
      "class": "observation",
      "clds": "BKN",
      "day_ind": "D",
      "dewPt": 46,
      "expire_time_gmt": 1773247860,
      "feels_like": 61,
      "gust": null,
      "heat_index": 61,
      "icon_extd": 2800,
      "key": "KLGA",
      "max_temp": null,
      "min_temp": null,
      "obs_id": "KLGA",
      "obs_name": "New York/LaGuardia",
      "precip_hrly": 0,
      "precip_total": null,
      "pressure": 29.89,
      "pressure_desc": "Falling Rapidly",
      "pressure_tend": 2,
      "primary_swell_direction": null,
      "primary_swell_height": null,
      "primary_swell_period": null,
      "primary_wave_height": null,
      "primary_wave_period": null,
      "qualifier": null,
      "qualifier_svrty": null,
      "rh": 58,
      "secondary_swell_direction": null,
      "secondary_swell_height": null,
      "secondary_swell_period": null,
      "snow_hrly": null,
      "temp": 61,
      "terse_phrase": null,
      "uv_desc": "Low",
      "uv_index": 1,
      "valid_time_gmt": 1773240660,
      "vis": 10,
      "water_temp": null,
      "wc": 61,
      "wdir": 110,
      "wdir_cardinal": "ESE",
      "wspd": 8,
      "wx_icon": 28,
      "wx_phrase": "Mostly Cloudy"
    },
    {
      "blunt_phrase": null,
      "class": "observation",
      "clds": "BKN",
      "day_ind": "D",
      "dewPt": 47,
      "expire_time_gmt": 1773251460,
      "feels_like": 62,
      "gust": null,
      "heat_index": 62,
      "icon_extd": 2800,
      "key": "KLGA",
      "max_temp": null,
      "min_temp": null,
      "obs_id": "KLGA",
      "obs_name": "New York/LaGuardia",
      "precip_hrly": 0,
      "precip_total": null,
      "pressure": 29.89,
      "pressure_desc": null,
      "pressure_tend": null,
      "primary_swell_direction": null,
      "primary_swell_height": null,
      "primary_swell_period": null,
      "primary_wave_height": null,
      "primary_wave_period": null,
      "qualifier": null,
      "qualifier_svrty": null,
      "rh": 58,
      "secondary_swell_direction": null,
      "secondary_swell_height": null,
      "secondary_swell_period": null,
      "snow_hrly": null,
      "temp": 62,
      "terse_phrase": null,
      "uv_desc": "Low",
      "uv_index": 2,
      "valid_time_gmt": 1773244260,
      "vis": 10,
      "water_temp": null,
      "wc": 62,
      "wdir": 190,
      "wdir_cardinal": "S",
      "wspd": 7,
      "wx_icon": 28,
      "wx_phrase": "Mostly Cloudy"
    },
    {
      "blunt_phrase": null,
      "class": "observation",
      "clds": "CLR",
      "day_ind": "D",
      "dewPt": 48,
      "expire_time_gmt": 1773255060,
      "feels_like": 61,
      "gust": null,
      "heat_index": 61,
      "icon_extd": 3400,
      "key": "KLGA",
      "max_temp": null,
      "min_temp": null,
      "obs_id": "KLGA",
      "obs_name": "New York/LaGuardia",
      "precip_hrly": 0,
      "precip_total": null,
      "pressure": 29.86,
      "pressure_desc": null,
      "pressure_tend": null,
      "primary_swell_direction": null,
      "primary_swell_height": null,
      "primary_swell_period": null,
      "primary_wave_height": null,
      "primary_wave_period": null,
      "qualifier": null,
      "qualifier_svrty": null,
      "rh": 62,
      "secondary_swell_direction": null,
      "secondary_swell_height": null,
      "secondary_swell_period": null,
      "snow_hrly": null,
      "temp": 61,
      "terse_phrase": null,
      "uv_desc": "Moderate",
      "uv_index": 4,
      "valid_time_gmt": 1773247860,
      "vis": 10,
      "water_temp": null,
      "wc": 61,
      "wdir": 100,
      "wdir_cardinal": "E",
      "wspd": 10,
      "wx_icon": 34,
      "wx_phrase": "Fair"
    },
    {
      "blunt_phrase": null,
      "class": "observation",
      "clds": "BKN",
      "day_ind": "D",
      "dewPt": 47,
      "expire_time_gmt": 1773258660,
      "feels_like": 59,
      "gust": null,
      "heat_index": 59,
      "icon_extd": 2800,
      "key": "KLGA",
      "max_temp": null,
      "min_temp": null,
      "obs_id": "KLGA",
      "obs_name": "New York/LaGuardia",
      "precip_hrly": 0,
      "precip_total": null,
      "pressure": 29.83,
      "pressure_desc": "Falling Rapidly",
      "pressure_tend": 2,
      "primary_swell_direction": null,
      "primary_swell_height": null,
      "primary_swell_period": null,
      "primary_wave_height": null,
      "primary_wave_period": null,
      "qualifier": null,
      "qualifier_svrty": null,
      "rh": 64,
      "secondary_swell_direction": null,
      "secondary_swell_height": null,
      "secondary_swell_period": null,
      "snow_hrly": null,
      "temp": 59,
      "terse_phrase": null,
      "uv_desc": "Low",
      "uv_index": 2,
      "valid_time_gmt": 1773251460,
      "vis": 10,
      "water_temp": null,
      "wc": 59,
      "wdir": 150,
      "wdir_cardinal": "SSE",
      "wspd": 7,
      "wx_icon": 28,
      "wx_phrase": "Mostly Cloudy"
    },
    {
      "blunt_phrase": null,
      "class": "observation",
      "clds": "BKN",
      "day_ind": "D",
      "dewPt": 48,
      "expire_time_gmt": 1773262260,
      "feels_like": 62,
      "gust": null,
      "heat_index": 62,
      "icon_extd": 2800,
      "key": "KLGA",
      "max_temp": null,
      "min_temp": null,
      "obs_id": "KLGA",
      "obs_name": "New York/LaGuardia",
      "precip_hrly": 0,
      "precip_total": null,
      "pressure": 29.79,
      "pressure_desc": null,
      "pressure_tend": null,
      "primary_swell_direction": null,
      "primary_swell_height": null,
      "primary_swell_period": null,
      "primary_wave_height": null,
      "primary_wave_period": null,
      "qualifier": null,
      "qualifier_svrty": null,
      "rh": 60,
      "secondary_swell_direction": null,
      "secondary_swell_height": null,
      "secondary_swell_period": null,
      "snow_hrly": null,
      "temp": 62,
      "terse_phrase": null,
      "uv_desc": "Low",
      "uv_index": 2,
      "valid_time_gmt": 1773255060,
      "vis": 10,
      "water_temp": null,
      "wc": 62,
      "wdir": 170,
      "wdir_cardinal": "S",
      "wspd": 12,
      "wx_icon": 28,
      "wx_phrase": "Mostly Cloudy"
    },
    {
      "blunt_phrase": null,
      "class": "observation",
      "clds": "BKN",
      "day_ind": "D",
      "dewPt": 49,
      "expire_time_gmt": 1773265860,
      "feels_like": 63,
      "gust": null,
      "heat_index": 63,
      "icon_extd": 2800,
      "key": "KLGA",
      "max_temp": null,
      "min_temp": null,
      "obs_id": "KLGA",
      "obs_name": "New York/LaGuardia",
      "precip_hrly": 0,
      "precip_total": null,
      "pressure": 29.75,
      "pressure_desc": null,
      "pressure_tend": null,
      "primary_swell_direction": null,
      "primary_swell_height": null,
      "primary_swell_period": null,
      "primary_wave_height": null,
      "primary_wave_period": null,
      "qualifier": null,
      "qualifier_svrty": null,
      "rh": 60,
      "secondary_swell_direction": null,
      "secondary_swell_height": null,
      "secondary_swell_period": null,
      "snow_hrly": null,
      "temp": 63,
      "terse_phrase": null,
      "uv_desc": "Low",
      "uv_index": 1,
      "valid_time_gmt": 1773258660,
      "vis": 10,
      "water_temp": null,
      "wc": 63,
      "wdir": 190,
      "wdir_cardinal": "S",
      "wspd": 13,
      "wx_icon": 28,
      "wx_phrase": "Mostly Cloudy"
    },
    {
      "blunt_phrase": null,
      "class": "observation",
      "clds": "BKN",
      "day_ind": "D",
      "dewPt": 52,
      "expire_time_gmt": 1773269460,
      "feels_like": 61,
      "gust": 24,
      "heat_index": 61,
      "icon_extd": 2800,
      "key": "KLGA",
      "max_temp": null,
      "min_temp": null,
      "obs_id": "KLGA",
      "obs_name": "New York/LaGuardia",
      "precip_hrly": 0,
      "precip_total": null,
      "pressure": 29.72,
      "pressure_desc": "Falling",
      "pressure_tend": 2,
      "primary_swell_direction": null,
      "primary_swell_height": null,
      "primary_swell_period": null,
      "primary_wave_height": null,
      "primary_wave_period": null,
      "qualifier": null,
      "qualifier_svrty": null,
      "rh": 72,
      "secondary_swell_direction": null,
      "secondary_swell_height": null,
      "secondary_swell_period": null,
      "snow_hrly": null,
      "temp": 61,
      "terse_phrase": null,
      "uv_desc": "Low",
      "uv_index": 1,
      "valid_time_gmt": 1773262260,
      "vis": 10,
      "water_temp": null,
      "wc": 61,
      "wdir": 180,
      "wdir_cardinal": "S",
      "wspd": 13,
      "wx_icon": 28,
      "wx_phrase": "Mostly Cloudy"
    },
    {
      "blunt_phrase": null,
      "class": "observation",
      "clds": "BKN",
      "day_ind": "D",
      "dewPt": 48,
      "expire_time_gmt": 1773273060,
      "feels_like": 57,
      "gust": null,
      "heat_index": 57,
      "icon_extd": 2800,
      "key": "KLGA",
      "max_temp": null,
      "min_temp": null,
      "obs_id": "KLGA",
      "obs_name": "New York/LaGuardia",
      "precip_hrly": 0,
      "precip_total": null,
      "pressure": 29.71,
      "pressure_desc": null,
      "pressure_tend": null,
      "primary_swell_direction": null,
      "primary_swell_height": null,
      "primary_swell_period": null,
      "primary_wave_height": null,
      "primary_wave_period": null,
      "qualifier": null,
      "qualifier_svrty": null,
      "rh": 72,
      "secondary_swell_direction": null,
      "secondary_swell_height": null,
      "secondary_swell_period": null,
      "snow_hrly": null,
      "temp": 57,
      "terse_phrase": null,
      "uv_desc": "Low",
      "uv_index": 0,
      "valid_time_gmt": 1773265860,
      "vis": 10,
      "water_temp": null,
      "wc": 57,
      "wdir": 170,
      "wdir_cardinal": "S",
      "wspd": 10,
      "wx_icon": 28,
      "wx_phrase": "Mostly Cloudy"
    },
    {
      "blunt_phrase": null,
      "class": "observation",
      "clds": "BKN",
      "day_ind": "D",
      "dewPt": 47,
      "expire_time_gmt": 1773276660,
      "feels_like": 54,
      "gust": null,
      "heat_index": 54,
      "icon_extd": 2800,
      "key": "KLGA",
      "max_temp": null,
      "min_temp": null,
      "obs_id": "KLGA",
      "obs_name": "New York/LaGuardia",
      "precip_hrly": 0,
      "precip_total": null,
      "pressure": 29.7,
      "pressure_desc": null,
      "pressure_tend": null,
      "primary_swell_direction": null,
      "primary_swell_height": null,
      "primary_swell_period": null,
      "primary_wave_height": null,
      "primary_wave_period": null,
      "qualifier": null,
      "qualifier_svrty": null,
      "rh": 77,
      "secondary_swell_direction": null,
      "secondary_swell_height": null,
      "secondary_swell_period": null,
      "snow_hrly": null,
      "temp": 54,
      "terse_phrase": null,
      "uv_desc": "Low",
      "uv_index": 0,
      "valid_time_gmt": 1773269460,
      "vis": 10,
      "water_temp": null,
      "wc": 54,
      "wdir": 170,
      "wdir_cardinal": "S",
      "wspd": 12,
      "wx_icon": 28,
      "wx_phrase": "Mostly Cloudy"
    },
    {
      "blunt_phrase": null,
      "class": "observation",
      "clds": "BKN",
      "day_ind": "N",
      "dewPt": 48,
      "expire_time_gmt": 1773280260,
      "feels_like": 55,
      "gust": null,
      "heat_index": 55,
      "icon_extd": 2700,
      "key": "KLGA",
      "max_temp": null,
      "min_temp": null,
      "obs_id": "KLGA",
      "obs_name": "New York/LaGuardia",
      "precip_hrly": 0,
      "precip_total": null,
      "pressure": 29.7,
      "pressure_desc": "Falling",
      "pressure_tend": 2,
      "primary_swell_direction": null,
      "primary_swell_height": null,
      "primary_swell_period": null,
      "primary_wave_height": null,
      "primary_wave_period": null,
      "qualifier": null,
      "qualifier_svrty": null,
      "rh": 77,
      "secondary_swell_direction": null,
      "secondary_swell_height": null,
      "secondary_swell_period": null,
      "snow_hrly": null,
      "temp": 55,
      "terse_phrase": null,
      "uv_desc": "Low",
      "uv_index": 0,
      "valid_time_gmt": 1773273060,
      "vis": 10,
      "water_temp": null,
      "wc": 55,
      "wdir": 170,
      "wdir_cardinal": "S",
      "wspd": 9,
      "wx_icon": 27,
      "wx_phrase": "Mostly Cloudy"
    },
    {
      "blunt_phrase": null,
      "class": "observation",
      "clds": "BKN",
      "day_ind": "N",
      "dewPt": 49,
      "expire_time_gmt": 1773283860,
      "feels_like": 55,
      "gust": null,
      "heat_index": 55,
      "icon_extd": 2700,
      "key": "KLGA",
      "max_temp": null,
      "min_temp": null,
      "obs_id": "KLGA",
      "obs_name": "New York/LaGuardia",
      "precip_hrly": 0.0,
      "precip_total": null,
      "pressure": 29.69,
      "pressure_desc": null,
      "pressure_tend": null,
      "primary_swell_direction": null,
      "primary_swell_height": null,
      "primary_swell_period": null,
      "primary_wave_height": null,
      "primary_wave_period": null,
      "qualifier": null,
      "qualifier_svrty": null,
      "rh": 80,
      "secondary_swell_direction": null,
      "secondary_swell_height": null,
      "secondary_swell_period": null,
      "snow_hrly": null,
      "temp": 55,
      "terse_phrase": null,
      "uv_desc": "Low",
      "uv_index": 0,
      "valid_time_gmt": 1773276660,
      "vis": 10,
      "water_temp": null,
      "wc": 55,
      "wdir": 170,
      "wdir_cardinal": "S",
      "wspd": 6,
      "wx_icon": 27,
      "wx_phrase": "Mostly Cloudy"
    },
    {
      "blunt_phrase": null,
      "class": "observation",
      "clds": "BKN",
      "day_ind": "N",
      "dewPt": 49,
      "expire_time_gmt": 1773287040,
      "feels_like": 54,
      "gust": null,
      "heat_index": 54,
      "icon_extd": 3540,
      "key": "KLGA",
      "max_temp": null,
      "min_temp": null,
      "obs_id": "KLGA",
      "obs_name": "New York/LaGuardia",
      "precip_hrly": 0.0,
      "precip_total": null,
      "pressure": 29.68,
      "pressure_desc": null,
      "pressure_tend": null,
      "primary_swell_direction": null,
      "primary_swell_height": null,
      "primary_swell_period": null,
      "primary_wave_height": null,
      "primary_wave_period": null,
      "qualifier": null,
      "qualifier_svrty": null,
      "rh": 83,
      "secondary_swell_direction": null,
      "secondary_swell_height": null,
      "secondary_swell_period": null,
      "snow_hrly": null,
      "temp": 54,
      "terse_phrase": null,
      "uv_desc": "Low",
      "uv_index": 0,
      "valid_time_gmt": 1773279840,
      "vis": 10,
      "water_temp": null,
      "wc": 54,
      "wdir": 160,
      "wdir_cardinal": "SSE",
      "wspd": 3,
      "wx_icon": 47,
      "wx_phrase": "Thunder"
    },
    {
      "blunt_phrase": null,
      "class": "observation",
      "clds": "BKN",
      "day_ind": "N",
      "dewPt": 49,
      "expire_time_gmt": 1773287460,
      "feels_like": 54,
      "gust": null,
      "heat_index": 54,
      "icon_extd": 401,
      "key": "KLGA",
      "max_temp": null,
      "min_temp": null,
      "obs_id": "KLGA",
      "obs_name": "New York/LaGuardia",
      "precip_hrly": 0.0,
      "precip_total": null,
      "pressure": 29.68,
      "pressure_desc": null,
      "pressure_tend": null,
      "primary_swell_direction": null,
      "primary_swell_height": null,
      "primary_swell_period": null,
      "primary_wave_height": null,
      "primary_wave_period": null,
      "qualifier": null,
      "qualifier_svrty": null,
      "rh": 83,
      "secondary_swell_direction": null,
      "secondary_swell_height": null,
      "secondary_swell_period": null,
      "snow_hrly": null,
      "temp": 54,
      "terse_phrase": null,
      "uv_desc": "Low",
      "uv_index": 0,
      "valid_time_gmt": 1773280260,
      "vis": 10,
      "water_temp": null,
      "wc": 54,
      "wdir": null,
      "wdir_cardinal": "CALM",
      "wspd": 0,
      "wx_icon": 4,
      "wx_phrase": "Light Rain with Thunder"
    },
    {
      "blunt_phrase": null,
      "class": "observation",
      "clds": "BKN",
      "day_ind": "N",
      "dewPt": 50,
      "expire_time_gmt": 1773289380,
      "feels_like": 55,
      "gust": null,
      "heat_index": 55,
      "icon_extd": 2700,
      "key": "KLGA",
      "max_temp": null,
      "min_temp": null,
      "obs_id": "KLGA",
      "obs_name": "New York/LaGuardia",
      "precip_hrly": 0.0,
      "precip_total": null,
      "pressure": 29.67,
      "pressure_desc": null,
      "pressure_tend": null,
      "primary_swell_direction": null,
      "primary_swell_height": null,
      "primary_swell_period": null,
      "primary_wave_height": null,
      "primary_wave_period": null,
      "qualifier": null,
      "qualifier_svrty": null,
      "rh": 83,
      "secondary_swell_direction": null,
      "secondary_swell_height": null,
      "secondary_swell_period": null,
      "snow_hrly": null,
      "temp": 55,
      "terse_phrase": null,
      "uv_desc": "Low",
      "uv_index": 0,
      "valid_time_gmt": 1773282180,
      "vis": 10,
      "water_temp": null,
      "wc": 55,
      "wdir": 120,
      "wdir_cardinal": "ESE",
      "wspd": 7,
      "wx_icon": 27,
      "wx_phrase": "Mostly Cloudy"
    },
    {
      "blunt_phrase": null,
      "class": "observation",
      "clds": "BKN",
      "day_ind": "N",
      "dewPt": 50,
      "expire_time_gmt": 1773291060,
      "feels_like": 54,
      "gust": null,
      "heat_index": 54,
      "icon_extd": 2700,
      "key": "KLGA",
      "max_temp": null,
      "min_temp": null,
      "obs_id": "KLGA",
      "obs_name": "New York/LaGuardia",
      "precip_hrly": 0.0,
      "precip_total": null,
      "pressure": 29.65,
      "pressure_desc": "Falling Rapidly",
      "pressure_tend": 2,
      "primary_swell_direction": null,
      "primary_swell_height": null,
      "primary_swell_period": null,
      "primary_wave_height": null,
      "primary_wave_period": null,
      "qualifier": null,
      "qualifier_svrty": null,
      "rh": 86,
      "secondary_swell_direction": null,
      "secondary_swell_height": null,
      "secondary_swell_period": null,
      "snow_hrly": null,
      "temp": 54,
      "terse_phrase": null,
      "uv_desc": "Low",
      "uv_index": 0,
      "valid_time_gmt": 1773283860,
      "vis": 10,
      "water_temp": null,
      "wc": 54,
      "wdir": 150,
      "wdir_cardinal": "SSE",
      "wspd": 8,
      "wx_icon": 27,
      "wx_phrase": "Mostly Cloudy"
    },
    {
      "blunt_phrase": null,
      "class": "observation",
      "clds": "BKN",
      "day_ind": "N",
      "dewPt": 50,
      "expire_time_gmt": 1773294660,
      "feels_like": 54,
      "gust": null,
      "heat_index": 54,
      "icon_extd": 2700,
      "key": "KLGA",
      "max_temp": null,
      "min_temp": null,
      "obs_id": "KLGA",
      "obs_name": "New York/LaGuardia",
      "precip_hrly": 0,
      "precip_total": null,
      "pressure": 29.63,
      "pressure_desc": null,
      "pressure_tend": null,
      "primary_swell_direction": null,
      "primary_swell_height": null,
      "primary_swell_period": null,
      "primary_wave_height": null,
      "primary_wave_period": null,
      "qualifier": null,
      "qualifier_svrty": null,
      "rh": 86,
      "secondary_swell_direction": null,
      "secondary_swell_height": null,
      "secondary_swell_period": null,
      "snow_hrly": null,
      "temp": 54,
      "terse_phrase": null,
      "uv_desc": "Low",
      "uv_index": 0,
      "valid_time_gmt": 1773287460,
      "vis": 10,
      "water_temp": null,
      "wc": 54,
      "wdir": 230,
      "wdir_cardinal": "SW",
      "wspd": 8,
      "wx_icon": 27,
      "wx_phrase": "Mostly Cloudy"
    }
  ]
}
